lulo/__init__.py
lulo/base.py
lulo/client.py
lulo/exceptions.py
lulo-1.0.dist-info/licenses/LICENCE
lulo-1.0.dist-info/METADATA
lulo-1.0.dist-info/WHEEL
lulo-1.0.dist-info/top_level.txt
lulo-1.0.dist-info/RECORD
