Metadata-Version: 2.4
Name: lulo
Version: 1.0
Summary: Lulo API Python client
Home-page: https://github.com/spacesudo/lulo
Author: Dave
Author-email: loony12_haricot@icloud.com
License: MIT
Project-URL: GitHub, https://github.com/spacesudo/lulo
Project-URL: Twitter, https://twitter.com/neverdusted
Project-URL: Documentation, https://dev.lulo.fi/
Keywords: lulo,solana,development,staking
Classifier: Intended Audience :: Developers
Classifier: Topic :: Software Development :: Build Tools
Classifier: License :: OSI Approved :: MIT License
Classifier: Programming Language :: Python :: 3
Classifier: Programming Language :: Python :: 3.7
Classifier: Programming Language :: Python :: 3.8
Classifier: Programming Language :: Python :: 3.9
Classifier: Programming Language :: Python :: 3 :: Only
Requires-Python: >=3.6, <4
License-File: LICENCE
Requires-Dist: requests
Requires-Dist: pydantic
Dynamic: author
Dynamic: author-email
Dynamic: classifier
Dynamic: description
Dynamic: description-content-type
Dynamic: home-page
Dynamic: keywords
Dynamic: license
Dynamic: license-file
Dynamic: project-url
Dynamic: requires-dist
Dynamic: requires-python
Dynamic: summary
